mira/__init__.py
mira/metrics.py
mira/pylint.py
mira/classifiers/__init__.py
mira/classifiers/classifier.py
mira/classifiers/clip.py
mira/classifiers/torchvision.py
mira/core/__init__.py
mira/core/annotation.py
mira/core/augmentations.py
mira/core/callbacks.py
mira/core/experimental.py
mira/core/files.py
mira/core/imagemeta.py
mira/core/resizing.py
mira/core/scene.py
mira/core/torchtools.py
mira/core/utils.py
mira/core/protos/scene_pb2.py
mira/datasets/__init__.py
mira/datasets/coco.py
mira/datasets/pixabay.py
mira/datasets/preloaded.py
mira/datasets/voc.py
mira/datasets/assets/coco_classes.txt
mira/datasets/assets/coco_classes_90.txt
mira/datasets/assets/imagenet1k_classes.txt
mira/datasets/assets/voc_classes.txt
mira/detectors/__init__.py
mira/detectors/common.py
mira/detectors/detector.py
mira/detectors/fasterrcnn.py
mira/detectors/retinanet.py
mira/detectors/segmentation.py
mira/detectors/assets/serve/README.md
mira/detectors/assets/serve/fasterrcnn.py
mira/detectors/assets/serve/object_detector.py
mira/detectors/assets/serve/retinanet.py
mira/detectors/assets/serve/smp.py
mira/detectors/experimental/__init__.py
mira/detectors/experimental/serving.py
mira/thirdparty/albumentations/.deepsource.toml
mira/thirdparty/albumentations/.git
mira/thirdparty/albumentations/.gitattributes
mira/thirdparty/albumentations/.gitignore
mira/thirdparty/albumentations/.pre-commit-config.yaml
mira/thirdparty/albumentations/.readthedocs.yml
mira/thirdparty/albumentations/LICENSE
mira/thirdparty/albumentations/MANIFEST.in
mira/thirdparty/albumentations/README.md
mira/thirdparty/albumentations/black.toml
mira/thirdparty/albumentations/setup.cfg
mira/thirdparty/albumentations/setup.py
mira/thirdparty/albumentations/.github/ISSUE_TEMPLATE/bug-report.md
mira/thirdparty/albumentations/.github/ISSUE_TEMPLATE/documentation.md
mira/thirdparty/albumentations/.github/workflows/ci.yml
mira/thirdparty/albumentations/.github/workflows/upload_to_pypi.yml
mira-0.9.34.dist-info/METADATA
mira-0.9.34.dist-info/WHEEL
mira-0.9.34.dist-info/licenses/LICENSE
mira-0.9.34.dist-info/RECORD
