Metadata-Version: 2.4
Name: mira
Version: 0.9.34
Summary: A package for simplifying object detection
Project-URL: Homepage, https://github.com/faustomorales/mira
Project-URL: Repository, https://github.com/faustomorales/mira
Author-email: Fausto Morales <faustomorales@gmail.com>
License-Expression: MIT
License-File: LICENSE
Classifier: Operating System :: MacOS
Classifier: Operating System :: Microsoft :: Windows
Classifier: Operating System :: POSIX :: Linux
Classifier: Operating System :: Unix
Classifier: Programming Language :: Python :: 3
Classifier: Programming Language :: Python :: 3 :: Only
Requires-Python: <3.12,>=3.8
Requires-Dist: matplotlib
Requires-Dist: numpy
Requires-Dist: pandas
Requires-Dist: protobuf
Requires-Dist: tqdm
Requires-Dist: twine>=6.1.0
Requires-Dist: validators
Provides-Extra: clip
Requires-Dist: ftfy; extra == 'clip'
Requires-Dist: regex; extra == 'clip'
Provides-Extra: detectors
Requires-Dist: pretrainedmodels==0.7.4; extra == 'detectors'
Requires-Dist: scikit-image; extra == 'detectors'
Requires-Dist: timm<0.10,>=0.9.2; extra == 'detectors'
Provides-Extra: segmentation
Requires-Dist: efficientnet-pytorch==0.7.1; extra == 'segmentation'
Requires-Dist: pretrainedmodels==0.7.4; extra == 'segmentation'
